aiearth/engine/__init__.py
aiearth/engine/aie_env.py
aiearth/engine/customfunction_node.py
aiearth/engine/export.py
aiearth/engine/function_helper.py
aiearth/engine/function_node.py
aiearth/engine/gen_python_functions.py
aiearth/engine/variable_node.py
aiearth/engine/aie_object/classifier.py
aiearth/engine/aie_object/collection.py
aiearth/engine/aie_object/confusion_matrix.py
aiearth/engine/aie_object/feature.py
aiearth/engine/aie_object/feature_collection.py
aiearth/engine/aie_object/filter.py
aiearth/engine/aie_object/geometry.py
aiearth/engine/aie_object/image.py
aiearth/engine/aie_object/image_collection.py
aiearth/engine/aie_object/kernel.py
aiearth/engine/aie_object/list.py
aiearth/engine/aie_object/model.py
aiearth/engine/aie_object/number.py
aiearth/engine/aie_object/projection.py
aiearth/engine/aie_object/reducer.py
aiearth/engine/aie_object/terrain.py
aiearth/engine/client/__init__.py
aiearth/engine/client/client.py
aiearth/engine/client/dataset.py
aiearth/engine/client/interactive_session.py
aiearth/engine/client/maps.py
aiearth/engine/client/task.py
aiearth/engine/map/__init__.py
aiearth/engine/map/aie_color.py
aiearth/engine/map/aie_layer.py
aiearth/engine/map/aie_map.py
aiearth/engine/map/apphub_embed_html.tpl
aiearth/engine/map/color.csv
aiearth/engine/serialize/__init__.py
aiearth/engine/serialize/gen_visitor.py
aiearth/engine/serialize/inspect.py
aiearth/engine/serialize/optimizer.py
aiearth/engine/serialize/serializer_impl.py
aiearth/engine/serialize/udf_manager.py
aiearth/engine/template/plugin_impl.py
aiearth/engine/udf_base/UDFImages_pb2.py
aiearth/engine/udf_base/__init__.py
aiearth/engine/udf_base/aie_udaf_base.py
aiearth/engine/udf_base/aie_udf_base.py
aiearth/engine/udf_base/annotation.py
aiearth/engine/udf_base/images.py
aiearth/engine/udf_base/udf_utils.py
aiearth_engine-3.1.6.dist-info/METADATA
aiearth_engine-3.1.6.dist-info/WHEEL
aiearth_engine-3.1.6.dist-info/top_level.txt
aiearth_engine-3.1.6.dist-info/RECORD
